[
  {
    "id": "ff35824d-5197-4ff3-bf84-a155ec55294e",
    "tool_name": "think",
    "timestamp": "2026-02-16T20:19:46.924002+00:00",
    "duration_ms": 0.084167,
    "success": true,
    "error_type": null,
    "params_hash": null,
    "handler_kind": "tool",
    "result_summary": null
  },
  {
    "id": "d0be959f-72ba-4f70-8e3b-3339aaeb7e51",
    "tool_name": "sequentialthinking",
    "timestamp": "2026-02-16T20:19:46.924392+00:00",
    "duration_ms": 0.087959,
    "success": true,
    "error_type": null,
    "params_hash": null,
    "handler_kind": "tool",
    "result_summary": null
  },
  {
    "id": "a6a370ae-50e8-4475-8bf3-ee74d88c9014",
    "tool_name": "sequentialthinking",
    "timestamp": "2026-02-16T20:19:47.041280+00:00",
    "duration_ms": 0.109083,
    "success": true,
    "error_type": null,
    "params_hash": null,
    "handler_kind": "tool",
    "result_summary": null
  },
  {
    "id": "84ad45b9-86fd-4341-aabd-55608184dd13",
    "tool_name": "execute_pre_commit_checks",
    "timestamp": "2026-02-16T20:19:55.276459+00:00",
    "duration_ms": 18159.273708,
    "success": true,
    "error_type": null,
    "params_hash": null,
    "handler_kind": "tool",
    "result_summary": null
  },
  {
    "id": "170cc2e2-0305-4b5f-bafa-c150b1d7ec31",
    "tool_name": "analyze_context_effectiveness",
    "timestamp": "2026-02-16T20:20:11.301651+00:00",
    "duration_ms": 1.921209,
    "success": true,
    "error_type": null,
    "params_hash": null,
    "handler_kind": "tool",
    "result_summary": null
  },
  {
    "id": "85b32dee-307d-4548-ac4e-0ff31bc23067",
    "tool_name": "get_context_usage_statistics",
    "timestamp": "2026-02-16T20:20:11.485142+00:00",
    "duration_ms": 3.421,
    "success": true,
    "error_type": null,
    "params_hash": null,
    "handler_kind": "tool",
    "result_summary": null
  },
  {
    "id": "0e7b9dcf-cbba-4084-bb90-f486cb5a0757",
    "tool_name": "get_structure_info",
    "timestamp": "2026-02-16T20:20:11.486530+00:00",
    "duration_ms": 3.846958,
    "success": true,
    "error_type": null,
    "params_hash": null,
    "handler_kind": "tool",
    "result_summary": null
  }
]